{
  "users": [
    {
      "id": 1,
      "name": "Valentina"
    },
    {
      "id": 2,
      "name": "Linlin"
    }
  ],
  "posts": [
    {
      "orginalId": "2baf70d1-42bb-4437-b551-e5fed5a87abe",
      "userId": 1,
      "userName": "Valentina",
      "image": "https://images2.alphacoders.com/103/thumb-350-1031480.jpg",
      "genre": "Romance",
      "content": "not nice",
      "rating": "1",
      "peopleUrl": "https://ghibliapi.herokuapp.com/people/",
      "animeInfo": {
        "title": "Castle in the Sky",
        "originalTitle": "天空の城ラピュタ",
        "director": "Hayao Miyazaki",
        "description": "The orphan Sheeta inherited a mysterious crystal that links her to the mythical sky-kingdom of Laputa. With the help of resourceful Pazu and a rollicking band of sky pirates, she makes her way to the ruins of the once-great civilization. Sheeta and Pazu must outwit the evil Muska, who plans to use Laputa's science to make himself ruler of the world."
      },
      "id": 2
    },
    {
      "orginalId": "ebbb6b7c-945c-41ee-a792-de0e43191bd8",
      "userId": 2,
      "userName": "Linlin",
      "image": "https://images.static-bluray.com/reviews/11337_1.jpg",
      "genre": "Magic",
      "content": "aa",
      "rating": "1",
      "peopleUrl": "https://ghibliapi.herokuapp.com/people/",
      "animeInfo": {
        "title": "Porco Rosso",
        "originalTitle": "紅の豚",
        "director": "Hayao Miyazaki",
        "description": "Porco Rosso, known in Japan as Crimson Pig (Kurenai no Buta) is the sixth animated film by Hayao Miyazaki and released in 1992. You're introduced to an Italian World War I fighter ace, now living as a freelance bounty hunter chasing 'air pirates' in the Adriatic Sea. He has been given a curse that changed his head to that of a pig. Once called Marco Pagot, he is now known to the world as 'Porco Rosso', Italian for 'Red Pig.'"
      },
      "id": 8
    }
  ]
}